{"stats":{"minecraft:picked_up":{"botania:red_mystical_flower":2,"botania:white_mystical_flower":2,"botania:light_gray_mystical_flower":6,"botania:blue_mystical_flower":2,"minecraft:dirt":2},"minecraft:killed":{"minecraft:wolf":1},"minecraft:custom":{"minecraft:time_since_rest":1531,"minecraft:play_time":6026,"minecraft:crouch_one_cm":72,"minecraft:sprint_one_cm":48871,"minecraft:deaths":1,"minecraft:damage_taken":250,"minecraft:walk_one_cm":11380,"minecraft:sneak_time":66,"minecraft:walk_under_water_one_cm":902,"minecraft:mob_kills":1,"minecraft:jump":140,"minecraft:damage_dealt":80,"minecraft:leave_game":1,"minecraft:time_since_death":1464,"minecraft:walk_on_water_one_cm":601,"minecraft:total_world_time":48934,"minecraft:swim_one_cm":1523,"minecraft:fall_one_cm":4610,"minecraft:fly_one_cm":24578},"minecraft:mined":{"minecraft:grass_block":1,"botania:white_mystical_flower":1,"botania:red_mystical_flower":1,"botania:blue_mystical_flower":1,"minecraft:birch_leaves":2,"minecraft:oak_leaves":1,"botania:light_gray_mystical_flower":3}},"DataVersion":3120}